README.md
setup.py
splashclient/__init__.py
splashclient/core.py
splashclient.egg-info/PKG-INFO
splashclient.egg-info/SOURCES.txt
splashclient.egg-info/dependency_links.txt
splashclient.egg-info/requires.txt
splashclient.egg-info/top_level.txt